csvalchemy/__init__.py
csvalchemy/cast.py
csvalchemy/reader.py
csvalchemy/result.py
csvalchemy/to_dict.py
csvalchemy/validator.py
csvalchemy/writer.py
csvalchemy-0.0.3.dist-info/METADATA
csvalchemy-0.0.3.dist-info/WHEEL
csvalchemy-0.0.3.dist-info/top_level.txt
csvalchemy-0.0.3.dist-info/RECORD
