Metadata-Version: 2.1
Name: csvalchemy
Version: 0.0.3
Summary: CSV ORM: Read, Validate, Update, and Write CSV files.
License: MIT License
Keywords: csv,validation,orm,model,pydantic,dataclass,typesdict,cast,reader
Requires-Python: >=3.10
Requires-Dist: pydantic>=2.9.2
Requires-Dist: dydactic>=0.1.2
